nonebot_plugin_naturel_gpt/__init__.py
nonebot_plugin_naturel_gpt/chat.py
nonebot_plugin_naturel_gpt/chat_manager.py
nonebot_plugin_naturel_gpt/command_func.py
nonebot_plugin_naturel_gpt/config.py
nonebot_plugin_naturel_gpt/Extension.py
nonebot_plugin_naturel_gpt/logger.py
nonebot_plugin_naturel_gpt/matcher.py
nonebot_plugin_naturel_gpt/matcher_MCRcon.py
nonebot_plugin_naturel_gpt/MCrcon/COPING.txt
nonebot_plugin_naturel_gpt/MCrcon/mcrcon.py
nonebot_plugin_naturel_gpt/openai_func.py
nonebot_plugin_naturel_gpt/persistent_data_manager.py
nonebot_plugin_naturel_gpt/preset_hub_funcs.py
nonebot_plugin_naturel_gpt/res/additional.css
nonebot_plugin_naturel_gpt/res/additional.html
nonebot_plugin_naturel_gpt/singleton.py
nonebot_plugin_naturel_gpt/store.py
nonebot_plugin_naturel_gpt/text_func.py
nonebot_plugin_naturel_gpt/text_to_image.py
nonebot_plugin_naturel_gpt/utils.py
nonebot_plugin_naturel_gpt-2.2.0.dist-info/LICENSE
nonebot_plugin_naturel_gpt-2.2.0.dist-info/METADATA
nonebot_plugin_naturel_gpt-2.2.0.dist-info/WHEEL
nonebot_plugin_naturel_gpt-2.2.0.dist-info/RECORD
